{
    "unicast" : "172.16.47.1",
    "logging" :
    {
        "level" : "trace",
        "console" : "true",
        "file" : { "enable" : "false", "path" : "vsomeip.log" },
        "dlt" : "false"
    },
    "applications" : 
    [
        {
            "name" : "vsomeipd",
            "id" : "0x0022"
        },
        {
            "name" : "service-sample",
            "id" : "0x1277"
        }
    ],
    "services" :
    [
        {
            "service" : 4660,
            "instance" : 22135,
            "reliable" : { "port" : "31000", "enable-magic-cookies" : "false" }
        },
        {
            "service" : 4660,
            "instance" : 22136,
            "reliable" : { "port" : "31000", "enable-magic-cookies" : "false" }
        },
        {
            "service" : 4660,
            "instance" : 22137,
            "reliable" : { "port" : "31000", "enable-magic-cookies" : "false" }
        }
    ],
    "routing" : "vsomeipd",
    "service-discovery" :
    {
        "enable" : "true"
    }
}
